mcp_server_ipinfo/__init__.py
mcp_server_ipinfo/cache.py
mcp_server_ipinfo/ipinfo.py
mcp_server_ipinfo/models.py
mcp_server_ipinfo/server.py
mseep_mcp_server_ipinfo-0.2.1.dist-info/licenses/LICENSE
mseep_mcp_server_ipinfo-0.2.1.dist-info/METADATA
mseep_mcp_server_ipinfo-0.2.1.dist-info/WHEEL
mseep_mcp_server_ipinfo-0.2.1.dist-info/entry_points.txt
mseep_mcp_server_ipinfo-0.2.1.dist-info/top_level.txt
mseep_mcp_server_ipinfo-0.2.1.dist-info/RECORD
