Metadata-Version: 2.4
Name: mseep-mcp-server-ipinfo
Version: 0.2.1
Summary: IP Geolocation Server for MCP
Author-email: mseep <support@skydeck.ai>
License: MIT License
Project-URL: Repository, https://github.com/briandconnelly/mcp-server-ipinfo.git
Project-URL: Issues, https://github.com/briandconnelly/mcp-server-ipinfo/issues
Classifier: Development Status :: 4 - Beta
Classifier: License :: OSI Approved :: MIT License
Classifier: Operating System :: OS Independent
Classifier: Programming Language :: Python
Classifier: Programming Language :: Python :: 3
Classifier: Programming Language :: Python :: 3.13
Classifier: Topic :: Software Development :: Libraries :: Python Modules
Classifier: Topic :: Scientific/Engineering :: Artificial Intelligence
Classifier: Topic :: System :: Networking
Requires-Python: >=3.13
License-File: LICENSE
Requires-Dist: fastmcp>=2.9.0
Requires-Dist: ipinfo>=5.1.1
Requires-Dist: pydantic>=2.10.6
Dynamic: license-file
